i3dFeatureExtraction/__init__.py
i3dFeatureExtraction/extract_features.py
i3dFeatureExtraction/extract_features_org.py
i3dFeatureExtraction/models/__init__.py
i3dFeatureExtraction/models/model_builder_video.py
i3dFeatureExtraction/models/nonlocal_helper.py
i3dFeatureExtraction/models/resnet.py
i3dFeatureExtraction/models/resnet_helper.py
i3dFeatureExtraction/models/resnet_video_org.py
i3dFeatureExtraction/utils/__init__.py
i3dFeatureExtraction/utils/convert_weights.py
i3dFeatureExtraction/utils/pretrained_existed.py
i3dFeatureExtraction-0.3.3.dist-info/LICENSE.txt
i3dFeatureExtraction-0.3.3.dist-info/METADATA
i3dFeatureExtraction-0.3.3.dist-info/WHEEL
i3dFeatureExtraction-0.3.3.dist-info/top_level.txt
i3dFeatureExtraction-0.3.3.dist-info/RECORD
