Metadata-Version: 2.1
Name: i3dFeatureExtraction
Version: 0.3.3
Summary: This package helps extract i3D features with ResNet-50 backbone given a folder of videos
Author: Hao Vy Phan
Author-email: vyhao03@gmail.com
Classifier: Programming Language :: Python :: 3
Classifier: License :: Freely Distributable
Classifier: Operating System :: Microsoft :: Windows
Requires-Python: >=3.8
License-File: LICENSE.txt
Requires-Dist: certifi ==2022.12.7
Requires-Dist: charset-normalizer ==2.1.1
Requires-Dist: click ==8.1.3
Requires-Dist: colorama ==0.4.6
Requires-Dist: contourpy ==1.0.7
Requires-Dist: cycler ==0.11.0
Requires-Dist: einops ==0.6.0
Requires-Dist: ffmpeg ==1.4
Requires-Dist: ffmpeg-python ==0.2.0
Requires-Dist: Flask ==2.2.2
Requires-Dist: Flask-SQLAlchemy ==2.5.1
Requires-Dist: fonttools ==4.39.3
Requires-Dist: future ==0.18.3
Requires-Dist: greenlet ==2.0.2
Requires-Dist: idna ==3.4
Requires-Dist: importlib-metadata ==6.3.0
Requires-Dist: itsdangerous ==2.1.2
Requires-Dist: Jinja2 ==3.1.2
Requires-Dist: kiwisolver ==1.4.4
Requires-Dist: MarkupSafe ==2.1.2
Requires-Dist: matplotlib ==3.6.2
Requires-Dist: natsort ==8.3.1
Requires-Dist: numpy ==1.23.4
Requires-Dist: packaging ==23.1
Requires-Dist: pandas ==1.5.1
Requires-Dist: pathlib ==1.0.1
Requires-Dist: pefile ==2023.2.7
Requires-Dist: Pillow ==9.5.0
Requires-Dist: pyparsing ==3.0.9
Requires-Dist: python-dateutil ==2.8.2
Requires-Dist: pytz ==2023.3
Requires-Dist: PyYAML ==6.0
Requires-Dist: requests ==2.28.1
Requires-Dist: six ==1.16.0
Requires-Dist: SQLAlchemy ==2.0.9
Requires-Dist: textwrap3
Requires-Dist: tqdm ==4.34.0
Requires-Dist: typing-extensions ==4.5.0
Requires-Dist: tzdata ==2023.3
Requires-Dist: urllib3 ==1.26.15
Requires-Dist: Werkzeug ==2.2.2
Requires-Dist: zipp ==3.15.0
